task3/ram.sv
module ram #(
    parameter   ADDRESS_WIDTH = 8,
                DATA_WIDTH = 8
)(
    input logic                     clk,
    input logic                     wr_en,
    input logic                     rd_en,
    input logic [ADDRESS_WIDTH-1:0] wr_addr,
    input logic [ADDRESS_WIDTH-1:0] offset,
    input logic [DATA_WIDTH-1:0]    din,
    output logic [DATA_WIDTH-1:0]   dout
);

logic [DATA_WIDTH-1:0] ram_array [2**ADDRESS_WIDTH:0];

always_ff @(posedge clk) begin
    if(wr_en== 1'b1)    
        ram_array[wr_addr] <= din;
    if(rd_en == 1'b1)
        //output is synchronous
        dout <=  ram_array[offset];
        
end
endmodule

task3/counter.sv
module counter #( //file name and module name must be the same
    parameter WIDTH = 8
) (
    //interface signals
    input  logic                clk,   //clock
    input  logic                rst,   //reset
    input  logic                en,    //counter enable
    //input  logic [WIDTH-1:0]    incr,  //counter increment
    output logic [WIDTH-1:0]    count  //count output

);

  always_ff @ (posedge clk) 
    if (rst) count <= {WIDTH{1'b0}};
    //else count <= count + {{WIDTH - 1{1'b0}}, en}; //count increments
    else if (en) count <= count + {1};

    //WIDTH-1{1'b0} tells you to replicate the value in curly brackets by WIDTH-1 times
    //so 1'b0 = 0, => WIDTH - 1 = 7 => 7 zeroes => 0b000,0000
    //and then concatenate the 'en' bit to either increment or stay the same.  

endmodule

task3/sigdelay.sv
module sigdelay #(
    parameter   A_WIDTH = 8,
                D_WIDTH = 8
)(
    input logic                 clk,    
    input logic                 rst,    //counter
    input logic                 en,     //counter
    input logic                 wr,
    input logic                 rd,
    input logic [D_WIDTH-1:0]   mic_signal,
    input logic [D_WIDTH-1:0]   offset, //offset into ram     
    output logic [D_WIDTH-1:0]  delayed_signal //dout for ram
);

    logic [A_WIDTH-1:0]         address; //interconnect wire for counter

counter addrCounter (
    .clk(clk),
    .rst (rst),
    .en (en),
    .count (address)
);

ram sigRam(
    .clk (clk),
    .wr_en (wr),
    .rd_en (rd),
    .wr_addr (address),
    .offset (offset),
    .din (mic_signal),
    .dout (delayed_signal)
);

endmodule

task3/sigdelay.vcd
$version Generated by VerilatedVcd $end
$date Fri Nov  1 10:22:05 2024 $end
$timescale 1ps $end

 $scope module TOP $end
  $var wire  1 # clk $end
  $var wire  8 * delayed_signal [7:0] $end
  $var wire  1 % en $end
  $var wire  8 ( mic_signal [7:0] $end
  $var wire  8 ) offset [7:0] $end
  $var wire  1 ' rd $end
  $var wire  1 $ rst $end
  $var wire  1 & wr $end
  $scope module sigdelay $end
   $var wire 32 , A_WIDTH [31:0] $end
   $var wire 32 , D_WIDTH [31:0] $end
   $var wire  8 + address [7:0] $end
   $var wire  1 # clk $end
   $var wire  8 * delayed_signal [7:0] $end
   $var wire  1 % en $end
   $var wire  8 ( mic_signal [7:0] $end
   $var wire  8 ) offset [7:0] $end
   $var wire  1 ' rd $end
   $var wire  1 $ rst $end
   $var wire  1 & wr $end
   $scope module addrCounter $end
    $var wire 32 , WIDTH [31:0] $end
    $var wire  1 # clk $end
    $var wire  8 + count [7:0] $end
    $var wire  1 % en $end
    $var wire  1 $ rst $end
   $upscope $end
   $scope module sigRam $end
    $var wire 32 , ADDRESS_WIDTH [31:0] $end
    $var wire 32 , DATA_WIDTH [31:0] $end
    $var wire  1 # clk $end
    $var wire  8 ( din [7:0] $end
    $var wire  8 * dout [7:0] $end
    $var wire  8 ) offset [7:0] $end
    $var wire  1 ' rd_en $end
    $var wire  8 + wr_addr [7:0] $end
    $var wire  1 & wr_en $end
   $upscope $end
  $upscope $end
 $upscope $end
$enddefinitions $end


#0
1#
0$
0%
1&
1'
b00000000 (
b01000000 )
b00000000 *
b00000000 +
b00000000000000000000000000001000 ,
#1
0#
#2
1#
b01111011 (
b00110011 )
#3
0#
#4
1#
b01101110 (
#5
0#
#6
1#
b01100010 (
#7
0#
#8
1#
b01010101 (
#9
0#
#10
1#
b01010011 (
#11
0#
#12
1#
b01011100 (
#13
0#
#14
1#
b01100010 (
#15
0#
#16
1#
b01101011 (
#17
0#
#18
1#
b01101000 (
#19
0#
#20
1#
#21
0#
#22
1#
b01100011 (
#23
0#
#24
1#
#25
0#
#26
1#
b01101010 (
#27
0#
#28
1#
b01101101 (
#29
0#
#30
1#
#31
0#
#32
1#
#33
0#
#34
1#
b01110000 (
#35
0#
#36
1#
b01110001 (
#37
0#
#38
1#
b01111010 (
#39
0#
#40
1#
b10000101 (
#41
0#
#42
1#
b10001110 (
#43
0#
#44
1#
b10001101 (
#45
0#
#46
1#
b10001001 (
#47
0#
#48
1#
b01111110 (
#49
0#
#50
1#
b01111010 (
#51
0#
#52
1#
#53
0#
#54
1#
b01111000 (
#55
0#
#56
1#
b01110010 (
#57
0#
#58
1#
b01101001 (
#59
0#
#60
1#
b01100001 (
#61
0#
#62
1#
b01100000 (
#63
0#
#64
1#
b01100001 (
#65
0#
#66
1#
b01100110 (
#67
0#
#68
1#
b01100101 (
#69
0#
#70
1#
b01100001 (
#71
0#
#72
1#
b01011111 (
#73
0#
#74
1#
b01100001 (
#75
0#
#76
1#
b01101000 (
#77
0#
#78
1#
b01110010 (
#79
0#
#80
1#
b01111001 (
#81
0#
#82
1#
b01111110 (
#83
0#
#84
1#
b01110101 (
#85
0#
#86
1#
b01110011 (
#87
0#
#88
1#
b01101100 (
#89
0#
#90
1#
b01100110 (
#91
0#
#92
1#
b01100101 (
#93
0#
#94
1#
b01100000 (
#95
0#
#96
1#
b01011101 (
#97
0#
#98
1#
b01010101 (
#99
0#
#100
1#
b01001101 (
#101
0#
#102
1#
#103
0#
#104
1#
b01010110 (
#105
0#
#106
1#
b01100000 (
#107
0#
#108
1#
b01101011 (
#109
0#
#110
1#
b01110101 (
#111
0#
#112
1#
b01111001 (
#113
0#
#114
1#
b01111111 (
#115
0#
#116
1#
b10000011 (
#117
0#
#118
1#
b10001000 (
#119
0#
#120
1#
b10000111 (
#121
0#
#122
1#
b10000100 (
#123
0#
#124
1#
b01111111 (
#125
0#
#126
1#
b01110110 (
#127
0#
#128
1#
b01110011 (
#129
0#
#130
1#
b01110101 (
#131
0#
#132
1#
b01111001 (
#133
0#
#134
1#
b01111111 (
#135
0#
#136
1#
b10000110 (
#137
0#
#138
1#
b10000100 (
#139
0#
#140
1#
b10001001 (
#141
0#
#142
1#
b10000100 (
#143
0#
#144
1#
b10000001 (
#145
0#
#146
1#
b10000000 (
#147
0#
#148
1#
b01111100 (
#149
0#
#150
1#
b01110101 (
#151
0#
#152
1#
b01110100 (
#153
0#
#154
1#
b01101010 (
#155
0#
#156
1#
#157
0#
#158
1#
#159
0#
#160
1#
b01110010 (
#161
0#
#162
1#
b01111010 (
#163
0#
#164
1#
#165
0#
#166
1#
b01111000 (
#167
0#
#168
1#
b01110100 (
#169
0#
#170
1#
b01101001 (
#171
0#
#172
1#
b01100011 (
#173
0#
#174
1#
b01100000 (
#175
0#
#176
1#
b01010111 (
#177
0#
#178
1#
b01010101 (
#179
0#
#180
1#
b01001110 (
#181
0#
#182
1#
b01001100 (
#183
0#
#184
1#
b01001110 (
#185
0#
#186
1#
#187
0#
#188
1#
b01010010 (
#189
0#
#190
1#
b01010100 (
#191
0#
#192
1#
b01011000 (
#193
0#
#194
1#
b01011100 (
#195
0#
#196
1#
b01100011 (
#197
0#
#198
1#
b01101010 (
#199
0#
#200
1#
b01110001 (
#201
0#
#202
1#
b01110101 (
#203
0#
#204
1#
b01110111 (
#205
0#
#206
1#
b01111010 (
#207
0#
#208
1#
#209
0#
#210
1#
b01110110 (
#211
0#
#212
1#
b01101111 (
#213
0#
#214
1#
b01101011 (
#215
0#
#216
1#
b01101100 (
#217
0#
#218
1#
b01101010 (
#219
0#
#220
1#
b01101011 (
#221
0#
#222
1#
b01110001 (
#223
0#
#224
1#
b01110111 (
#225
0#
#226
1#
b01111111 (
#227
0#
#228
1#
b01111011 (
#229
0#
#230
1#
b01110010 (
#231
0#
#232
1#
b01101010 (
#233
0#
#234
1#
b01100011 (
#235
0#
#236
1#
b01100010 (
#237
0#
#238
1#
b01011111 (
#239
0#
#240
1#
b01100001 (
#241
0#
#242
1#
b01100011 (
#243
0#
#244
1#
b01100001 (
#245
0#
#246
1#
b01100000 (
#247
0#
#248
1#
b01100001 (
#249
0#
#250
1#
b01100100 (
#251
0#
#252
1#
#253
0#
#254
1#
b01100001 (
#255
0#
#256
1#
b01100100 (
#257
0#
#258
1#
b01100000 (
#259
0#
#260
1#
b01100010 (
#261
0#
#262
1#
b01100101 (
#263
0#
#264
1#
b01101010 (
#265
0#
#266
1#
b01110000 (
#267
0#
#268
1#
b01110011 (
#269
0#
#270
1#
b01110101 (
#271
0#
#272
1#
b01111100 (
#273
0#
#274
1#
b01111010 (
#275
0#
#276
1#
b01110111 (
#277
0#
#278
1#
b01110001 (
#279
0#
#280
1#
b01110010 (
#281
0#
#282
1#
#283
0#
#284
1#
b01111010 (
#285
0#
#286
1#
b10000000 (
#287
0#
#288
1#
b10000010 (
#289
0#
#290
1#
b10001011 (
#291
0#
#292
1#
b10001000 (
#293
0#
#294
1#
b10001010 (
#295
0#
#296
1#
b10000111 (
#297
0#
#298
1#
b01111101 (
#299
0#
#300
1#
b01110100 (
#301
0#
#302
1#
b01101000 (
#303
0#
#304
1#
b01100010 (
#305
0#
#306
1#
b01011101 (
#307
0#
#308
1#
b01011001 (
#309
0#
#310
1#
b01011100 (
#311
0#
#312
1#
b01100101 (
#313
0#
#314
1#
b01101000 (
#315
0#
#316
1#
b00110010 )
#317
0#
#318
1#
b01101110 (
#319
0#
#320
1#
b01110010 (
b00110001 )
#321
0#
#322
1#
b01110001 (
b00101110 )
#323
0#
#324
1#
b01101111 (
b00101010 )
#325
0#
#326
1#
b01100110 (
#327
0#
#328
1#
b01100001 (
b00101001 )
#329
0#
#330
1#
b01011101 (
#331
0#
#332
1#
b01011011 (
#333
0#
#334
1#
b01100100 (
#335
0#
#336
1#
b01101000 (
#337
0#
#338
1#
b01101011 (
#339
0#
#340
1#
b01110000 (
#341
0#
#342
1#
b01101111 (
#343
0#
#344
1#
b01110001 (
#345
0#
#346
1#
b01101110 (
#347
0#
#348
1#
b01100111 (
#349
0#
#350
1#
b01100011 (
#351
0#
#352
1#
b01011011 (
b00101000 )
#353
0#
#354
1#
b01010111 (
b00100111 )
#355
0#
#356
1#
b01010010 (
b00100101 )
#357
0#
#358
1#
b01010100 (
b00100001 )
#359
0#
#360
1#
b01010010 (
#361
0#
#362
1#
b01011000 (
#363
0#
#364
1#
b01100001 (
#365
0#
#366
1#
b01101000 (
#367
0#
#368
1#
b01101001 (
#369
0#
#370
1#
b01110011 (
#371
0#
#372
1#
b01111011 (
#373
0#
#374
1#
b01111101 (
#375
0#
#376
1#
#377
0#
#378
1#
b10000001 (
#379
0#
#380
1#
b10000100 (
b00100000 )
#381
0#
#382
1#
b10000111 (
b00011111 )
#383
0#
#384
1#
b00011001 )
#385
0#
#386
1#
b10001010 (
b00011000 )
#387
0#
#388
1#
b10000010 (
#389
0#
#390
1#
b01111001 (
#391
0#
#392
1#
b01110000 (
#393
0#
#394
1#
b01101001 (
#395
0#
#396
1#
b01100111 (
#397
0#
#398
1#
b01101010 (
#399
0#
#400
1#
#401
0#
#402
1#
b01101001 (
#403
0#
#404
1#
b01100110 (
#405
0#
#406
1#
b01100011 (
#407
0#
#408
1#
b00010100 )
#409
0#
#410
1#
b01100111 (
b00010010 )
#411
0#
#412
1#
b01101001 (
#413
0#
#414
1#
b01101011 (
#415
0#
#416
1#
b01101010 (
#417
0#
#418
1#
b01100101 (
#419
0#
#420
1#
b01100000 (
#421
0#
#422
1#
b01011111 (
#423
0#
#424
1#
b01100101 (
#425
0#
#426
1#
b01101001 (
#427
0#
#428
1#
b01101100 (
#429
0#
#430
1#
b01101111 (
#431
0#
#432
1#
b00010001 )
#433
0#
#434
1#
b01110001 (
b00010000 )
#435
0#
#436
1#
b01101101 (
b00001100 )
#437
0#
#438
1#
b01101010 (
b00001010 )
#439
0#
#440
1#
b01100101 (
#441
0#
#442
1#
b01100100 (
#443
0#
#444
1#
b01100011 (
#445
0#
#446
1#
b01011111 (
#447
0#
#448
1#
b01100100 (
#449
0#
#450
1#
b01101001 (
#451
0#
#452
1#
b01110000 (
#453
0#
#454
1#
b01110101 (
#455
0#
#456
1#
b01111001 (
#457
0#
#458
1#
b01111010 (
b00001001 )
#459
0#
#460
1#
b01110111 (
b00000110 )
#461
0#
#462
1#
b01110010 (
b00000001 )
#463
0#
#464
1#
#465
0#
#466
1#
b01110011 (
#467
0#
#468
1#
b01110100 (
#469
0#
#470
1#
b01110000 (
#471
0#
#472
1#
b01101100 (
#473
0#
#474
1#
b01101001 (
#475
0#
#476
1#
b01101010 (
#477
0#
#478
1#
b01101011 (
#479
0#
#480
1#
b01101100 (
#481
0#
#482
1#
b01101001 (
b00000000 )
#483
0#
#484
1#
b01100111 (
b01101100 *
#485
0#
#486
1#
b01100000 (
b01101001 *
#487
0#
#488
1#
b01011101 (
b01100111 *
#489
0#
#490
1#
b01100000 *
#491
0#
#492
1#
b01100001 (
b01011101 *
#493
0#
#494
1#
b01101010 (
#495
0#
#496
1#
b01110010 (
b01100001 *
#497
0#
#498
1#
b01110110 (
b01101010 *
#499
0#
#500
1#
b01110111 (
b01110010 *
#501
0#
#502
1#
b01110110 (
b01110110 *
#503
0#
#504
1#
b01110111 *
#505
0#
#506
1#
b01110010 (
b01110110 *
#507
0#
#508
1#
b01110100 (
#509
0#
#510
1#
b01110011 (
b01110010 *
#511
0#
#512
1#
b01101101 (
b01110100 *
#513
0#
#514
1#
b01101111 (
b01110011 *
#515
0#
#516
1#
b01110001 (
b01101101 *
#517
0#
#518
1#
b01110100 (
b01101111 *
#519
0#
#520
1#
b01110001 *
#521
0#
#522
1#
b01110101 (
b01110100 *
#523
0#
#524
1#
b01111001 (
#525
0#
#526
1#
b01110111 (
b01110101 *
#527
0#
#528
1#
b01111010 (
b01111001 *
#529
0#
#530
1#
b01110111 *
#531
0#
#532
1#
b01110011 (
b01111010 *
#533
0#
#534
1#
b01101111 (
#535
0#
#536
1#
b01101101 (
b01110011 *
#537
0#
#538
1#
b01101100 (
b01101111 *
#539
0#
#540
1#
b01101101 (
b01101101 *
#541
0#
#542
1#
b01101110 (
b01101100 *
#543
0#
#544
1#
b01110011 (
b01101101 *
#545
0#
#546
1#
b01110111 (
b01101110 *
#547
0#
#548
1#
b01111010 (
b01110011 *
#549
0#
#550
1#
b01110111 (
b01110111 *
#551
0#
#552
1#
b01110000 (
b01111010 *
#553
0#
#554
1#
b01101011 (
b01110111 *
#555
0#
#556
1#
b01101101 (
b01110000 *
#557
0#
#558
1#
b01101100 (
b01101011 *
#559
0#
#560
1#
b01110011 (
b01101101 *
#561
0#
#562
1#
b01101100 *
#563
0#
#564
1#
b01110000 (
b01110011 *
#565
0#
#566
1#
b01101100 (
#567
0#
#568
1#
b01100111 (
b01110000 *
#569
0#
#570
1#
b01100001 (
b01101100 *
#571
0#
#572
1#
b01011101 (
b01100111 *
#573
0#
#574
1#
b01011100 (
b01100001 *
#575
0#
#576
1#
b01011101 (
b01011101 *
#577
0#
#578
1#
b01100001 (
b01011100 *
#579
0#
#580
1#
b01100110 (
b01011101 *
#581
0#
#582
1#
b01101001 (
b01100001 *
#583
0#
#584
1#
b01101110 (
b01100110 *
#585
0#
#586
1#
b01110100 (
b01101001 *
#587
0#
#588
1#
b01111011 (
b01101110 *
#589
0#
#590
1#
b01111100 (
b01110100 *
#591
0#
#592
1#
b01111101 (
b01111011 *
#593
0#
#594
1#
b01110110 (
b01111100 *
#595
0#
#596
1#
b01101111 (
b01111101 *
#597
0#
#598
1#
b01100111 (
b01110110 *
#599
0#
#600
1#
b01101011 (
b01101111 *
#601
0#
#602
1#
b01101000 (
b01100111 *
#603
0#
#604
1#
b01101011 *
#605
0#
#606
1#
b01101100 (
b01101000 *
#607
0#
#608
1#
b01101000 (
#609
0#
#610
1#
b01100111 (
b01101100 *
#611
0#
#612
1#
b01100100 (
b01101000 *
#613
0#
#614
1#
b01100011 (
b01100111 *
#615
0#
#616
1#
b01100101 (
b01100100 *
#617
0#
#618
1#
b01100100 (
b01100011 *
#619
0#
#620
1#
b01100110 (
b01100101 *
#621
0#
#622
1#
b01100101 (
b01100100 *
#623
0#
#624
1#
b01100110 *
#625
0#
#626
1#
b01101010 (
b01100101 *
#627
0#
#628
1#
b01110001 (
#629
0#
#630
1#
b01110100 (
b01101010 *
#631
0#
#632
1#
b01110111 (
b01110001 *
#633
0#
#634
1#
b01110110 (
b01110100 *
#635
0#
#636
1#
b01110000 (
b01110111 *
#637
0#
#638
1#
b01101011 (
b01110110 *
#639
0#
#640
1#
b01101010 (
b01110000 *
#641
0#
#642
1#
b01101011 *
#643
0#
#644
1#
b01101011 (
b01101010 *
#645
0#
#646
1#
b01101100 (
#647
0#
#648
1#
b01101110 (
b01101011 *
#649
0#
#650
1#
b01110001 (
b01101100 *
#651
0#
#652
1#
b01110111 (
b01101110 *
#653
0#
#654
1#
b01111001 (
b01110001 *
#655
0#
#656
1#
b01110111 (
b01110111 *
#657
0#
#658
1#
b01110010 (
b01111001 *
#659
0#
#660
1#
b01101111 (
b01110111 *
#661
0#
#662
1#
b01101010 (
b01110010 *
#663
0#
#664
1#
b01100110 (
b01101111 *
#665
0#
#666
1#
b01101100 (
b01101010 *
#667
0#
#668
1#
b01101101 (
b01100110 *
#669
0#
#670
1#
b01110100 (
b01101100 *
#671
0#
#672
1#
b01111001 (
b01101101 *
#673
0#
#674
1#
b01111100 (
b01110100 *
#675
0#
#676
1#
b01111111 (
b01111001 *
#677
0#
#678
1#
b01111011 (
b01111100 *
#679
0#
#680
1#
b01111100 (
b01111111 *
#681
0#
#682
1#
b01110110 (
b01111011 *
#683
0#
#684
1#
b01101100 (
b01111100 *
#685
0#
#686
1#
b01100111 (
b01110110 *
#687
0#
#688
1#
b01100100 (
b01101100 *
#689
0#
#690
1#
b01100110 (
b01100111 *
#691
0#
#692
1#
b01101000 (
b01100100 *
#693
0#
#694
1#
b01101101 (
b01100110 *
#695
0#
#696
1#
b01110101 (
b01101000 *
#697
0#
#698
1#
b01111000 (
b01101101 *
#699
0#
#700
1#
b01110110 (
b01110101 *
#701
0#
#702
1#
b01111000 (
b01111000 *
#703
0#
#704
1#
b01111001 (
b01110110 *
#705
0#
#706
1#
b01110011 (
b01111000 *
#707
0#
#708
1#
b01111001 *
#709
0#
#710
1#
b01111000 (
b01110011 *
#711
0#
#712
1#
b01111001 (
#713
0#
#714
1#
b01111010 (
b01111000 *
#715
0#
#716
1#
b01111011 (
b01111001 *
#717
0#
#718
1#
b01111110 (
b01111010 *
#719
0#
#720
1#
b01111100 (
b01111011 *
#721
0#
#722
1#
b01111001 (
b01111110 *
#723
0#
#724
1#
b01110001 (
b01111100 *
#725
0#
#726
1#
b01101001 (
b01111001 *
#727
0#
#728
1#
b01011111 (
b01110001 *
#729
0#
#730
1#
b01011100 (
b01101001 *
#731
0#
#732
1#
b01011000 (
b01011111 *
#733
0#
#734
1#
b01011111 (
b01011100 *
#735
0#
#736
1#
b01100001 (
b01011000 *
#737
0#
#738
1#
b01101001 (
b01011111 *
#739
0#
#740
1#
b01101100 (
b01100001 *
#741
0#
#742
1#
b01101011 (
b01101001 *
#743
0#
#744
1#
b01101100 *
#745
0#
#746
1#
b01100101 (
b01101011 *
#747
0#
#748
1#
b01101000 (
#749
0#
#750
1#
b01101111 (
b01100101 *
#751
0#
#752
1#
b01110011 (
b01101000 *
#753
0#
#754
1#
b01110101 (
b01101111 *
#755
0#
#756
1#
b01110001 (
b01110011 *
#757
0#
#758
1#
b01110101 (
b01110101 *
#759
0#
#760
1#
b01110100 (
b01110001 *
#761
0#
#762
1#
b01110111 (
b01110101 *
#763
0#
#764
1#
b01110110 (
b01110100 *
#765
0#
#766
1#
b01110100 (
b01110111 *
#767
0#
#768
1#
b01110010 (
b01110110 *
#769
0#
#770
1#
b01110000 (
b01110100 *
#771
0#
#772
1#
b01101101 (
b01110010 *
#773
0#
#774
1#
b01110000 *
#775
0#
#776
1#
b01101111 (
b01101101 *
#777
0#
#778
1#
b01110011 (
#779
0#
#780
1#
b01101111 *
#781
0#
#782
1#
b01110010 (
b01110011 *
#783
0#
#784
1#
b01101111 (
#785
0#
#786
1#
b01101010 (
b01110010 *
#787
0#
#788
1#
b01101100 (
b01101111 *
#789
0#
#790
1#
b01101101 (
b01101010 *
#791
0#
#792
1#
b01110100 (
b01101100 *
#793
0#
#794
1#
b01110111 (
b01101101 *
#795
0#
#796
1#
b01111101 (
b01110100 *
#797
0#
#798
1#
b01111100 (
b01110111 *
#799
0#
#800
1#
b01111101 *
#801
0#
#802
1#
b01111110 (
b01111100 *
#803
0#
#804
1#
b01111011 (
#805
0#
#806
1#
b01110101 (
b01111110 *
#807
0#
#808
1#
b01101011 (
b01111011 *
#809
0#
#810
1#
b01100101 (
b01110101 *
#811
0#
#812
1#
b01011011 (
b01101011 *
#813
0#
#814
1#
b01011000 (
b01100101 *
#815
0#
#816
1#
b01011011 (
b01011011 *
#817
0#
#818
1#
b01011110 (
b01011000 *
#819
0#
#820
1#
b01100001 (
b01011011 *
#821
0#
#822
1#
b01100100 (
b01011110 *
#823
0#
#824
1#
b01101010 (
b01100001 *
#825
0#
#826
1#
b01101110 (
b01100100 *
#827
0#
#828
1#
b01110001 (
b01101010 *
#829
0#
#830
1#
b01110011 (
b01101110 *
#831
0#
#832
1#
b01101111 (
b01110001 *
#833
0#
#834
1#
b01101011 (
b01110011 *
#835
0#
#836
1#
b01101100 (
b01101111 *
#837
0#
#838
1#
b01101101 (
b01101011 *
#839
0#
#840
1#
b01110001 (
b01101100 *
#841
0#
#842
1#
b01110101 (
b01101101 *
#843
0#
#844
1#
b01110001 *
#845
0#
#846
1#
b01110000 (
b01110101 *
#847
0#
#848
1#
b01101010 (
#849
0#
#850
1#
b01100001 (
b01110000 *
#851
0#
#852
1#
b01011011 (
b01101010 *
#853
0#
#854
1#
b01011010 (
b01100001 *
#855
0#
#856
1#
b01011011 (
b01011011 *
#857
0#
#858
1#
b01011010 *
#859
0#
#860
1#
b01011010 (
b01011011 *
#861
0#
#862
1#
b01011001 (
#863
0#
#864
1#
b01100000 (
b01011010 *
#865
0#
#866
1#
b01101000 (
b01011001 *
#867
0#
#868
1#
b01101101 (
b01100000 *
#869
0#
#870
1#
b01110000 (
b01101000 *
#871
0#
#872
1#
b01101011 (
b01101101 *
#873
0#
#874
1#
b01100110 (
b01110000 *
#875
0#
#876
1#
b01100011 (
b01101011 *
#877
0#
#878
1#
b01011111 (
b01100110 *
#879
0#
#880
1#
b01100010 (
b01100011 *
#881
0#
#882
1#
b01101010 (
b01011111 *
#883
0#
#884
1#
b01110001 (
b01100010 *
#885
0#
#886
1#
b01110101 (
b01101010 *
#887
0#
#888
1#
b01110001 *
#889
0#
#890
1#
b01110010 (
b01110101 *
#891
0#
#892
1#
b01101100 (
#893
0#
#894
1#
b01101000 (
b01110010 *
#895
0#
#896
1#
b01100100 (
b01101100 *
#897
0#
#898
1#
b01101000 *
#899
0#
#900
1#
b01011101 (
b01100100 *
#901
0#
#902
1#
b01011000 (
#903
0#
#904
1#
b00000001 )
b01011101 *
#905
0#
#906
1#
b01011011 (
b00000000 *
#907
0#
#908
1#
b01100001 (
#909
0#
#910
1#
b01100101 (
#911
0#
#912
1#
b01101101 (
#913
0#
#914
1#
b01110001 (
#915
0#
#916
1#
b01110000 (
#917
0#
#918
1#
b01101111 (
#919
0#
#920
1#
b01110000 (
#921
0#
#922
1#
b01101101 (
#923
0#
#924
1#
b01101010 (
#925
0#
#926
1#
b01101100 (
#927
0#
#928
1#
b01110000 (
#929
0#
#930
1#
#931
0#
#932
1#
b01101111 (
#933
0#
#934
1#
b01100111 (
#935
0#
#936
1#
b01100011 (
#937
0#
#938
1#
b01011111 (
#939
0#
#940
1#
b01011100 (
#941
0#
#942
1#
b01100000 (
#943
0#
#944
1#
b01100001 (
#945
0#
#946
1#
b01100010 (
#947
0#
#948
1#
b01100101 (
#949
0#
#950
1#
b01100100 (
#951
0#
#952
1#
b01101010 (
#953
0#
#954
1#
b01100111 (
#955
0#
#956
1#
b01101000 (
#957
0#
#958
1#
#959
0#
#960
1#
b01100011 (
#961
0#
#962
1#
b01011111 (
#963
0#
#964
1#
b01100001 (
#965
0#
#966
1#
b01011110 (
#967
0#
#968
1#
b01011111 (
#969
0#
#970
1#
b01100001 (
#971
0#
#972
1#
b01100011 (
#973
0#
#974
1#
b01100110 (
#975
0#
#976
1#
b01101011 (
#977
0#
#978
1#
b01101010 (
#979
0#
#980
1#
b01101001 (
#981
0#
#982
1#
b01101011 (
#983
0#
#984
1#
b01101101 (
#985
0#
#986
1#
b01110010 (
#987
0#
#988
1#
b01110110 (
#989
0#
#990
1#
#991
0#
#992
1#
b01110011 (
#993
0#
#994
1#
b01101111 (
#995
0#
#996
1#
b01101110 (
#997
0#
#998
1#
b01110101 (
#999
0#
#1000
1#
b01111000 (
#1001
0#
#1002
1#
b01111001 (
#1003
0#
#1004
1#
b01110111 (
#1005
0#
#1006
1#
b01110001 (
#1007
0#
#1008
1#
b01101011 (
#1009
0#
#1010
1#
#1011
0#
#1012
1#
b01101000 (
#1013
0#
#1014
1#
b01100111 (
#1015
0#
#1016
1#
b01100101 (
#1017
0#
#1018
1#
#1019
0#
#1020
1#
b01100001 (
#1021
0#
#1022
1#
b01100000 (
#1023
0#
#1024
1#
b01101000 (
#1025
0#
#1026
1#
b01010101 (
#1027
0#
#1028
1#
b01001001 (
#1029
0#
#1030
1#
b01000001 (
#1031
0#
#1032
1#
b01011100 (
#1033
0#
#1034
1#
b01111101 (
#1035
0#
#1036
1#
b10010010 (
#1037
0#
#1038
1#
b10110001 (
#1039
0#
#1040
1#
b10110000 (
#1041
0#
#1042
1#
b10011010 (
#1043
0#
#1044
1#
b01111001 (
#1045
0#
#1046
1#
b01011100 (
#1047
0#
#1048
1#
b01001110 (
#1049
0#
#1050
1#
b01001011 (
#1051
0#
#1052
1#
b01001111 (
#1053
0#
#1054
1#
b01010101 (
#1055
0#
#1056
1#
b01011011 (
#1057
0#
#1058
1#
b01011101 (
b00000000 )
#1059
0#
#1060
1#
b01011111 (
b01011011 *
#1061
0#
#1062
1#
b01100100 (
b01011101 *
#1063
0#
#1064
1#
b01110111 (
b01011111 *
#1065
0#
#1066
1#
b10000111 (
b01100100 *
#1067
0#
#1068
1#
b10010011 (
b01110111 *
#1069
0#
#1070
1#
b10010111 (
b10000111 *
#1071
0#
#1072
1#
b10001111 (
b10010011 *
#1073
0#
#1074
1#
b10000010 (
b10010111 *
#1075
0#
#1076
1#
b01101101 (
b10001111 *
#1077
0#
#1078
1#
b01100000 (
b10000010 *
#1079
0#
#1080
1#
b01011101 (
b01101101 *
#1081
0#
#1082
1#
b01011011 (
b01100000 *
#1083
0#
#1084
1#
b01011110 (
b01011101 *
#1085
0#
#1086
1#
b01100011 (
b01011011 *
#1087
0#
#1088
1#
b01100111 (
b01011110 *
#1089
0#
#1090
1#
b01100011 *
#1091
0#
#1092
1#
b01101011 (
b01100111 *
#1093
0#
#1094
1#
b01110110 (
#1095
0#
#1096
1#
b01111111 (
b01101011 *
#1097
0#
#1098
1#
b10001011 (
b01110110 *
#1099
0#
#1100
1#
b10001111 (
b01111111 *
#1101
0#
#1102
1#
b10001101 (
b10001011 *
#1103
0#
#1104
1#
b10000001 (
b10001111 *
#1105
0#
#1106
1#
b01101110 (
b10001101 *
#1107
0#
#1108
1#
b01100001 (
b10000001 *
#1109
0#
#1110
1#
b01010101 (
b01101110 *
#1111
0#
#1112
1#
b01010010 (
b01100001 *
#1113
0#
#1114
1#
b01010011 (
b00000001 )
b01010101 *
#1115
0#
#1116
1#
b01011000 (
b00000000 *
#1117
0#
#1118
1#
b01011110 (
#1119
0#
#1120
1#
b01100100 (
#1121
0#
#1122
1#
b01101010 (
#1123
0#
#1124
1#
b01110000 (
#1125
0#
#1126
1#
b01111000 (
#1127
0#
#1128
1#
b01111101 (
#1129
0#
#1130
1#
#1131
0#
#1132
1#
b01110111 (
#1133
0#
#1134
1#
b01101101 (
#1135
0#
#1136
1#
b01100110 (
#1137
0#
#1138
1#
b01011111 (
#1139
0#
#1140
1#
b01011101 (
#1141
0#
#1142
1#
b01100010 (
#1143
0#
#1144
1#
b01101000 (
#1145
0#
#1146
1#
b01101101 (
#1147
0#
#1148
1#
b01101111 (
#1149
0#
#1150
1#
b01110000 (
#1151
0#
#1152
1#
b01101101 (
#1153
0#
#1154
1#
b01101010 (
#1155
0#
#1156
1#
b01101000 (
#1157
0#
#1158
1#
b01100110 (
#1159
0#
#1160
1#
b01100011 (
b00000000 )
#1161
0#
#1162
1#
b01100110 *
#1163
0#
#1164
1#
b01100011 *
#1165
0#
#1166
1#
b01100010 (
#1167
0#
#1168
1#
b01100000 (
#1169
0#
#1170
1#
b01011111 (
b01100010 *
#1171
0#
#1172
1#
b01011011 (
b01100000 *
#1173
0#
#1174
1#
b01010110 (
b01011111 *
#1175
0#
#1176
1#
b01001111 (
b01011011 *
#1177
0#
#1178
1#
b01000011 (
b01010110 *
#1179
0#
#1180
1#
b00111001 (
b01001111 *
#1181
0#
#1182
1#
b01010001 (
b01000011 *
#1183
0#
#1184
1#
b01110110 (
b00111001 *
#1185
0#
#1186
1#
b10001010 (
b01010001 *
#1187
0#
#1188
1#
b10101000 (
b01110110 *
#1189
0#
#1190
1#
b10101110 (
b10001010 *
#1191
0#
#1192
1#
b10011000 (
b10101000 *
#1193
0#
#1194
1#
b01111001 (
b10101110 *
#1195
0#
#1196
1#
b01011100 (
b10011000 *
#1197
0#
#1198
1#
b01001101 (
b01111001 *
#1199
0#
